{
  "width": 128,
  "height": 128,

  "terrain": {
    "fill": 0,
    "patches": [
      {
        "tileId": 1,
        "x": 20,
        "y": 20,
        "w": 30,
        "h": 18
      },
      {
        "tileId": 1,
        "x": 70,
        "y": 60,
        "w": 22,
        "h": 22
      }
    ]
  },

  "occluders": [
    {
      "x": 10,
      "y": 10
    },
    {
      "x": 11,
      "y": 10
    },
    {
      "x": 12,
      "y": 10
    }
  ],

  "resources": [
    {
      "type": "food",
      "x": 15,
      "y": 15,
      "amount": 8
    },
    {
      "type": "textile",
      "x": 16,
      "y": 15,
      "amount": 4
    }
  ]
}
